development/__init__.py
development/normalize_sandbox_fusion.py
development/utils/__init__.py
development/utils/generate_api_key.py
development/utils/subprocess_manager.py
eval_protocol/__init__.py
eval_protocol/__main__.py
eval_protocol/_version.py
eval_protocol/auth.py
eval_protocol/cli.py
eval_protocol/common_utils.py
eval_protocol/config.py
eval_protocol/directory_utils.py
eval_protocol/evaluation.py
eval_protocol/exceptions.py
eval_protocol/fireworks_rft.py
eval_protocol/gcp_tools.py
eval_protocol/generic_server.py
eval_protocol/get_pep440_version.py
eval_protocol/logging_utils.py
eval_protocol/mcp_env.py
eval_protocol/models.py
eval_protocol/packaging.py
eval_protocol/platform_api.py
eval_protocol/playback_policy.py
eval_protocol/resources.py
eval_protocol/reward_function.py
eval_protocol/rl_processing.py
eval_protocol/server.py
eval_protocol/typed_interface.py
eval_protocol/adapters/__init__.py
eval_protocol/adapters/base.py
eval_protocol/adapters/bigquery.py
eval_protocol/adapters/braintrust.py
eval_protocol/adapters/dataframe.py
eval_protocol/adapters/fireworks_tracing.py
eval_protocol/adapters/huggingface.py
eval_protocol/adapters/langchain.py
eval_protocol/adapters/langfuse.py
eval_protocol/adapters/langsmith.py
eval_protocol/adapters/openai_responses.py
eval_protocol/adapters/trl.py
eval_protocol/adapters/utils.py
eval_protocol/adapters/weave.py
eval_protocol/agent/__init__.py
eval_protocol/agent/models.py
eval_protocol/agent/orchestrator.py
eval_protocol/agent/resource_abc.py
eval_protocol/agent/resource_pool.py
eval_protocol/agent/task_manager.py
eval_protocol/agent/tool_registry.py
eval_protocol/agent/resources/__init__.py
eval_protocol/agent/resources/bfcl_sim_api_resource.py
eval_protocol/agent/resources/docker_resource.py
eval_protocol/agent/resources/filesystem_resource.py
eval_protocol/agent/resources/python_state_resource.py
eval_protocol/agent/resources/sql_resource.py
eval_protocol/agent/resources/bfcl_envs/__init__.py
eval_protocol-0.3.9.dist-info/licenses/LICENSE
eval_protocol-0.3.9.dist-info/METADATA
eval_protocol-0.3.9.dist-info/WHEEL
eval_protocol-0.3.9.dist-info/entry_points.txt
eval_protocol-0.3.9.dist-info/top_level.txt
eval_protocol-0.3.9.dist-info/RECORD
